metadata_cleaner/__init__.py
metadata_cleaner/cli.py
metadata_cleaner/config/__init__.py
metadata_cleaner/config/settings.py
metadata_cleaner/core/__init__.py
metadata_cleaner/core/metadata_filter.py
metadata_cleaner/core/metadata_utils.py
metadata_cleaner/file_handlers/__init__.py
metadata_cleaner/file_handlers/audio_handler.py
metadata_cleaner/file_handlers/docx_handler.py
metadata_cleaner/file_handlers/image_handler.py
metadata_cleaner/file_handlers/pdf_handler.py
metadata_cleaner/file_handlers/video_handler.py
metadata_cleaner/logs/__init__.py
metadata_cleaner/logs/logger.py
metadata_cleaner/remover.py
metadata_cleaner-2.0.3.dist-info/LICENSE
metadata_cleaner-2.0.3.dist-info/METADATA
metadata_cleaner-2.0.3.dist-info/WHEEL
metadata_cleaner-2.0.3.dist-info/entry_points.txt
metadata_cleaner-2.0.3.dist-info/RECORD
