Metadata-Version: 2.3
Name: metadata-cleaner
Version: 2.0.3
Summary: A CLI tool to remove or selectively filter metadata from images, documents, audio, and video files.
License: MIT
Author: Sandeep Paidipati
Author-email: sandeep.paidipati@gmail.com
Requires-Python: >=3.7
Classifier: License :: OSI Approved :: MIT License
Classifier: Programming Language :: Python :: 3
Classifier: Programming Language :: Python :: 3.7
Classifier: Programming Language :: Python :: 3.8
Classifier: Programming Language :: Python :: 3.9
Classifier: Programming Language :: Python :: 3.10
Classifier: Programming Language :: Python :: 3.11
Classifier: Programming Language :: Python :: 3.12
Classifier: Programming Language :: Python :: 3.13
Requires-Dist: click (>=8.1.3,<9.0.0)
Requires-Dist: mutagen (>=1.45.1,<2.0.0)
Requires-Dist: piexif (>=1.1.3,<2.0.0)
Requires-Dist: pillow (>=9.5.0,<10.0.0)
Requires-Dist: pymediainfo (>=5.0.3,<6.0.0)
Requires-Dist: pypdf (>=3.12.0,<4.0.0)
Requires-Dist: python-docx (>=0.8.11,<0.9.0)
Requires-Dist: tqdm (>=4.64.0,<5.0.0)
Project-URL: Homepage, https://github.com/sandy-sp/metadata-cleaner
Project-URL: Repository, https://github.com/sandy-sp/metadata-cleaner
